drf_useful_decorators/__init__.py
drf_useful_decorators/decorators.py
drf_useful_decorators/methods.py
drf_useful_decorators-0.0.6.dist-info/LICENSE
drf_useful_decorators-0.0.6.dist-info/METADATA
drf_useful_decorators-0.0.6.dist-info/WHEEL
drf_useful_decorators-0.0.6.dist-info/top_level.txt
drf_useful_decorators-0.0.6.dist-info/RECORD
